victorforever/__init__.py
victor4ever-1.0.0.dist-info/METADATA
victor4ever-1.0.0.dist-info/WHEEL
victor4ever-1.0.0.dist-info/entry_points.txt
victor4ever-1.0.0.dist-info/top_level.txt
victor4ever-1.0.0.dist-info/RECORD
