Metadata-Version: 2.1
Name: victor4ever
Version: 1.0.0
Summary: Victor Forever
Home-page: https://youtu.be/xvFZjo5PgG0
Author: Ward Van Driessche
Author-email: wardvandriessche@gmail.com
